{
  "$schema": "./node_modules/@biomejs/biome/configuration_schema.json",
  "vcs": {
    "enabled": true,
    "clientKind": "git",
    "useIgnoreFile": true
  },
  "files": {
    "ignoreUnknown": false,
    "includes": [
      "**",
      "!**/node_modules",
      "!**/dist",
      "!**/.turbo",
      "!**/.vscode",
      "!**/routeTree.gen.ts",
      "!**/client-factory.ts",
      "!**/api-schemas.ts",
      "!**/opensrc"
    ]
  },
  "formatter": {
    "enabled": true,
    "indentStyle": "space"
  },
  "linter": {
    "enabled": true,
    "rules": {
      "recommended": true,
      "complexity": {
        "noBannedTypes": "off"
      }
    }
  },
  "css": {
    "parser": {
      "tailwindDirectives": true
    }
  },
  "javascript": {
    "formatter": {
      "quoteStyle": "double"
    }
  },
  "assist": {
    "enabled": true,
    "actions": {
      "source": {
        "organizeImports": "on"
      }
    }
  }
}
